xy_django_app_information/__init__.py
xy_django_app_information/abstracts.py
xy_django_app_information/admin.py
xy_django_app_information/apps.py
xy_django_app_information/models.py
xy_django_app_information/serializers.py
xy_django_app_information/tests.py
xy_django_app_information/views.py
xy_django_app_information/migrations/__init__.py
xy_django_app_information-1.0.3.dist-info/LICENSE
xy_django_app_information-1.0.3.dist-info/METADATA
xy_django_app_information-1.0.3.dist-info/WHEEL
xy_django_app_information-1.0.3.dist-info/top_level.txt
xy_django_app_information-1.0.3.dist-info/RECORD
